AprsLibrary/AprsLibrary.py
AprsLibrary/__init__.py
robotframework_aprslib-0.9.1.dist-info/LICENSE
robotframework_aprslib-0.9.1.dist-info/METADATA
robotframework_aprslib-0.9.1.dist-info/WHEEL
robotframework_aprslib-0.9.1.dist-info/top_level.txt
robotframework_aprslib-0.9.1.dist-info/RECORD
