Metadata-Version: 2.1
Name: robotframework-aprslib
Version: 0.9.1
Summary: Robot Framework keywords for the 'aprslib' Python Library
Home-page: https://github.com/joergschultzelutter/robotframework-aprslib
Author: Joerg Schultze-Lutter
Author-email: joerg.schultze.lutter@gmail.com
License: GNU General Public License v3 (GPLv3)
Keywords: Ham Radio,Amateur Radio,APRS,Robot Framework
Classifier: Intended Audience :: Developers
Classifier: Programming Language :: Python :: 3
Classifier: Natural Language :: English
Classifier: License :: OSI Approved :: GNU General Public License v3 (GPLv3)
Classifier: Operating System :: OS Independent
Classifier: Development Status :: 4 - Beta
Classifier: Framework :: Robot Framework
Classifier: Framework :: Robot Framework :: Library
Classifier: Topic :: Software Development
Classifier: Topic :: Software Development :: Testing
Classifier: Topic :: Software Development :: Quality Assurance
Classifier: Topic :: Communications :: Ham Radio
License-File: LICENSE
Requires-Dist: robotframework (>=3.2)
Requires-Dist: aprslib (>=0.7.0)
